Metadata-Version: 2.1
Name: aiotoml
Version: 0.0.0
Summary: Works with TOML in the async style
Home-page: https://github.com/Rhinik/aiotoml
Author: Kurbatov Yan
Author-email: deknowny@gmail.com
License: Apache=2.0
Keywords: aio async toml
Platform: UNKNOWN
Requires-Python: >=3.8
